{
  "id": "giodel-e-4a2c278b",
  "nickname": "002 🚀 Math🔹74 - Popul🔹Гёдель Эше🔹4a2c278b",
  "path": "002 🚀 Mathimatics/74 - Popular. Mathimatics/Гёдель Эшер Бах эта бесконечная гирлянда (Даглас Р. Хофштадтер).djvu",
  "home": "../data/biblioteka-main",
  "cover": "giodel-esher-bakh-eta-beskonechnaia-girlianda-daglas-r-khofshtadter-djvu-4a2c278b.jpg",
  "Cover.name": "giodel-e-4a2c278b.jpg",
  "title": "Гёдель Эшер Бах эта бесконечная гирлянда (Даглас Р. Хофштадтер).djvu"
}