{
  "id": "c-prakti-9c7797e2",
  "nickname": "003 🪁 Comp🔹41 - C++ L🔹C++. Практ🔹9c7797e2",
  "path": "003 🪁 Computer Science/41 - C++ Lang/C++. Практика многопоточного программирования (Энтони Уильямс).ddjvu.pdf",
  "home": "../data/biblioteka-main",
  "type": "file",
  "cover": "c-prakti-9c7797e2.jpg",
  "cover_ratio": 1.415,
  "title": "C++. Практика многопоточного программирования (Энтони Уильямс).ddjvu.pdf"
}