{
  "id": "kak-priv-165ce7de",
  "nickname": "003 🪁 Comp🔹304 - Down🔹Как привес🔹165ce7de",
  "path": "003 🪁 Computer Science/304 - Down IT - 29 dec/Как привести дела в порядок — в школе и не только (Дэвид Аллен Майк Уильямс Марк Уоллас).pdf",
  "home": "../data/biblioteka-main",
  "cover": "kak-privesti-dela-v-poriadok-v-shkole-i-ne-tolko-devid-allen-maik-uiliams-mark-uollas-pdf-165ce7de.jpg",
  "Cover.name": "kak-priv-165ce7de.jpg",
  "title": "Как привести дела в порядок — в школе и не только (Дэвид Аллен Майк Уильямс Марк Уоллас).pdf"
}