{
  "id": "kak-stat-3d2c2168",
  "nickname": "down-23-ja🔹Как стать 🔹3d2c2168",
  "path": "down-23-jan/Как стать первоклассным руководителем. Правила привлечения и удержания лучших специалистов (Джеффри Дж. Фо.epub",
  "home": "../data/biblioteka-main",
  "cover": "kak-stat-3d2c2168.jpg",
  "cover_ratio": 1.578,
  "Cover.name": "kak-stat-3d2c2168.jpg",
  "title": "Как стать первоклассным руководителем. Правила привлечения и удержания лучших специалистов (Джеффри Дж. Фо.epub"
}